fastybird_metadata/__init__.py
fastybird_metadata/accounts_module.py
fastybird_metadata/devices_module.py
fastybird_metadata/enum.py
fastybird_metadata/exceptions.py
fastybird_metadata/loader.py
fastybird_metadata/py.typed
fastybird_metadata/routing.py
fastybird_metadata/triggers_module.py
fastybird_metadata/types.py
fastybird_metadata/validator.py
fastybird_metadata/resources/application.json
fastybird_metadata/resources/schemas/application.json
fastybird_metadata/resources/schemas/actions/action.channel.control.json
fastybird_metadata/resources/schemas/actions/action.channel.property.json
fastybird_metadata/resources/schemas/actions/action.connector.control.json
fastybird_metadata/resources/schemas/actions/action.connector.property.json
fastybird_metadata/resources/schemas/actions/action.device.control.json
fastybird_metadata/resources/schemas/actions/action.device.property.json
fastybird_metadata/resources/schemas/actions/action.trigger.control.json
fastybird_metadata/resources/schemas/modules/accounts-module/entity.account.json
fastybird_metadata/resources/schemas/modules/accounts-module/entity.email.json
fastybird_metadata/resources/schemas/modules/accounts-module/entity.identity.json
fastybird_metadata/resources/schemas/modules/accounts-module/entity.role.json
fastybird_metadata/resources/schemas/modules/devices-module/entity.channel.control.json
fastybird_metadata/resources/schemas/modules/devices-module/entity.channel.json
fastybird_metadata/resources/schemas/modules/devices-module/entity.channel.property.json
fastybird_metadata/resources/schemas/modules/devices-module/entity.connector.control.json
fastybird_metadata/resources/schemas/modules/devices-module/entity.connector.json
fastybird_metadata/resources/schemas/modules/devices-module/entity.connector.property.json
fastybird_metadata/resources/schemas/modules/devices-module/entity.device.attribute.json
fastybird_metadata/resources/schemas/modules/devices-module/entity.device.control.json
fastybird_metadata-0.77.0.dist-info/LICENSE.md
fastybird_metadata-0.77.0.dist-info/METADATA
fastybird_metadata-0.77.0.dist-info/WHEEL
fastybird_metadata-0.77.0.dist-info/top_level.txt
fastybird_metadata-0.77.0.dist-info/RECORD
