Metadata-Version: 2.1
Name: fastybird-metadata
Version: 0.77.0
Summary: FastyBird metadata reader & validator for modules, plugins & etc. used by FastyBird applications
Home-page: https://github.com/FastyBird/metadata
Author: FastyBird
Author-email: code@fastybird.com
License: Apache Software License (Apache Software License 2.0)
Download-URL: https://github.com/FastyBird/metadata/archive/0.77.0.tar.gz
Platform: UNKNOWN
Classifier: Development Status :: 3 - Alpha
Classifier: Environment :: Console
Classifier: Intended Audience :: Developers
Classifier: Intended Audience :: Education
Classifier: Intended Audience :: Education
Classifier: License :: OSI Approved :: Apache Software License
Classifier: Operating System :: OS Independent
Classifier: Programming Language :: Python
Classifier: Programming Language :: Python :: 3.7
Classifier: Programming Language :: Python :: 3.8
Classifier: Programming Language :: Python :: 3.9
Classifier: Programming Language :: Python :: 3.10
Classifier: Programming Language :: Python :: 3 :: Only
Classifier: Topic :: Communications
Classifier: Topic :: Home Automation
Classifier: Topic :: System :: Hardware
Requires-Python: >=3.7
License-File: LICENSE.md
Requires-Dist: fastjsonschema
Requires-Dist: fastnumbers
Requires-Dist: setuptools
Requires-Dist: types-setuptools
